RTL/cla_top.v
module gen_prop_unit(
    input clk,
    input [15:0] a, b,
    //output reg [15:0] g, p
    output  [15:0] g, p
);
    assign g = a & b;  // bitwise generator
    assign p = a ^ b;  // bitwise propagator

endmodule

    // always @(posedge clk) begin
    //     g <= a & b;  // bitwise generator
    //     p <= a ^ b;  // bitwise propagator
    // end
/*
if you want to make gen_prop_unit a clocked unit,
uncomment the g and p in the always block, your layered testbench
will receive the sum one posedge clock later from the DUT.
Thus mismatch will happen.clk

Here, I have removed the clocking from the gen_prop_unit,
kept the clocking in only the summation_unit. It works.
Also made sure lineart testbench is working in the negedge.
And Summation Unit is working in the posedge instead of negedge as before.

Note that, for sampling, monitor and drivers are also working in the
negedge actually.

*/



module base4_carry_unit(
    input      [3:0] g,  // Generate signals
    input      [3:0] p,  // Propagate signals
    input            cin, // Carry-in
    output     [4:1] cout // Carry-out vector
);

    // assign cout [1] = g[0] | (p[0] & cin);
    // assign cout [2] = g[1] | (p[1] & (g[0] | (p[0] & cin)));
    // assign cout [3] = g[2] | (p[2] & (g[1] | (p[1] & (g[0] | (p[0] & cin)))));
    // assign cout[4] = (g[3] | ( p[3] & g[2] ) | ( p[3] & p[2] & g[1] ) |
    // ( p[3] & p[2] & p[1] & g[0] )) | ((p[3] & p[2] & p[1] & p[0]) & cin);

    assign cout [1] = g[0] | (p[0] & cin);
    assign cout [2] = g[1] | (p[1] & cout[1]);
    assign cout [3] = g[2] | (p[2] & cout[2]);
    assign cout [4] = g[3] | (p[3] & cout[3]);

endmodule


module summation_unit (
    input      [15:0] p,          // Input vector p
    input             cin,        // Carry-in signal
    input      [16:1] cout,       // Carry-out vector for each bit (except for the first bit)
    input             clk,        // Clock signal
    output reg [15:0] sum,        // Output sum vector
    output            carry_out16
);
    integer i;
    //reg [7:0] sum_op;
    always @(posedge clk) begin  //changed to posedge for driver and monitor
        sum[0] <= p[0] ^ cin;  // First bit sum using carry-in

        for (i = 1; i < 16; i = i + 1) begin
            sum[i] <= p[i] ^ cout[i];  // Remaining bits sum using cout[i]
        end
    end
    assign carry_out16 = cout[16];

endmodule



// 16 bit top module
module cla_top (
    input      [15:0] a, b,      // 16-bit input operands
    input             cin,       // Carry-in input
    input             clk,       // Clock signal
    output reg [15:0] sum,       // 16-bit output sum
    output            carry_out16
);

    // Internal wires to connect modules
    wire [15:0] g, p;                           // Generate and Propagate signals for 16 bits
    wire [4:1] cout1, cout2, cout3, cout4;      // Carry-out for 4-bit sections
    wire       cout_mid1, cout_mid2, cout_mid3; // Carry between the 4-bit sections
    // wire       signed_carry_out;                // Final carry out for signed overflow detection
    // wire       signed_overflow;                 // To detect overflow in signed addition

    // Instantiate the generate and propagate unit for 16 bits
    gen_prop_unit gen_prop_inst (
        .a(a),
        .b(b),
        .g(g),
        .p(p)
    );

    // Instantiate the base4 carry unit for the lower 4 bits (a[3:0], b[3:0])
    base4_carry_unit carry_unit1 (
        .g(g[3:0]),
        .p(p[3:0]),
        .cin(cin),             // The initial carry-in
        .cout(cout1)           // Carry out for lower 4 bits
    );

    // Carry-out from the first unit (cout1[4]) becomes the carry-in for the second unit
    assign cout_mid1 = cout1[4];

    // Instantiate the base4 carry unit for the next 4 bits (a[7:4], b[7:4])
    base4_carry_unit carry_unit2 (
        .g(g[7:4]),
        .p(p[7:4]),
        .cin(cout_mid1),        // Carry-out from the first unit as carry-in
        .cout(cout2)            // Carry out for bits [7:4]
    );

    // Carry-out from the second unit (cout2[4]) becomes the carry-in for the third unit
    assign cout_mid2 = cout2[4];

    // Instantiate the base4 carry unit for the next 4 bits (a[11:8], b[11:8])
    base4_carry_unit carry_unit3 (
        .g(g[11:8]),
        .p(p[11:8]),
        .cin(cout_mid2),        // Carry-out from the second unit as carry-in
        .cout(cout3)            // Carry out for bits [11:8]
    );

    // Carry-out from the third unit (cout3[4]) becomes the carry-in for the fourth unit
    assign cout_mid3 = cout3[4];

    // Instantiate the base4 carry unit for the upper 4 bits (a[15:12], b[15:12])
    base4_carry_unit carry_unit4 (
        .g(g[15:12]),
        .p(p[15:12]),
        .cin(cout_mid3),        // Carry-out from the third unit as carry-in
        .cout(cout4)            // Carry out for bits [15:12]
    );

    // Instantiate the summation unit to calculate the final 16-bit sum
    summation_unit sum_unit (
        .p(p),                 // Propagate signal from the gen_prop_unit
        .cin(cin),             // Carry-in
        .cout({cout4[4:1], cout3[4:1], cout2[4:1], cout1[4:1]}),  // Carry-out bits from all carry units
        .clk(clk),
        .sum(sum),              // Output sum
        .carry_out16(carry_out16)
    );

endmodule

SelfcheckingTB/cla_top_tb.sv
module cla_top_tb;

    // Test inputs
    logic [15:0] a, b;   // 8-bit input operands
    logic       cin;          // Carry-in input
    logic       clk;          // Clock signal
    logic [15:0] sum;   // Output sum
    logic       carry_out16;

    // Instantiate the cla_top module
    cla_top dut (
        .a(a),
        .b(b),
        .cin(cin),
        .clk(clk),
        .sum(sum),
        .carry_out16(carry_out16)
    );

    // Clock generation
    initial begin
        clk = 0;
        forever #5 clk = ~clk; // Toggle clock every 5 time units
    end

    // Test sequence
    initial begin
        // Display header
        $display("--------------- CLA Testbench Results ---------------");
        $display("Time\t a (Binary)\t             b (Binary)\t       cin\t sum (Binary)\t sum (Decimal)\t carry_out\t");

        // Test Case 1: a = 10, b = 12, cin = 0
        @(negedge clk);  //$display("Time is %t", $time);
        a = 16'b00001010; // 10
        b = 16'b00001100; // 12
        cin = 0;
        #10; // Wait for one clock cycle
        check_output(a+b+cin); // Expected sum = 10 + 12 = 22

        @(negedge clk);  //$display("Time is %t", $time);
        a = 500;
        b = 600;
        cin = 0;
        #10; // Wait for one clock cycle
        check_output(a+b+cin);

        @(negedge clk);  //$display("Time is %t", $time);
        a = 30500;
        b = 20499;
        cin = 1;
        #10; // Wait for one clock cycle
        check_output(a+b+cin);

        @(negedge clk);  //$display("Time is %t", $time);
        a = 65000;
        b = 10;
        cin = 1;
        #10; // Wait for one clock cycle
        check_output(a+b+cin);

        @(negedge clk);  //$display("Time is %t", $time);
        a = 0;
        b = 0;
        cin = 1;
        #10; // Wait for one clock cycle
        check_output(a+b+cin);

        @(negedge clk);  //$display("Time is %t", $time);
        a = 65120;
        b = 3000;
        cin = 1;
        #10; // Wait for one clock cycle
        check_output(a+b+cin);

        @(negedge clk);  //$display("Time is %t", $time);
        a = 65535;
        b = 0;
        cin = 1;
        #10; // Wait for one clock cycle
        check_output(a+b+cin);

        #10;
        $finish;
    end

    // Task to check output
    task check_output(input [16:0] expected_sum);
        // Display current results
        $display("%0t\t %b\t %b\t %b\t %b\t %0d\t          %b\t       ", $time, a, b, cin, sum, sum, carry_out16);

        // Compare actual and expected output
        if ((sum !== expected_sum[15:0]) | (carry_out16 !== expected_sum[16])) begin
            $display("\033[1;31mFAIL: Expected sum = %b, got sum = %b\033[0m", expected_sum[15:0], sum);
            $display("\033[1;31m---------------------------------------------------------\033[0m");
        end else begin
            $display("\033[1;32mPASS: sum = %b\033[0m", sum);
            $display("\033[1;32m---------------------------------------------------------\033[0m");
        end
    endtask

      // VCD dump
    initial begin
    $dumpfile("cla_directed_tb.vcd");
    $dumpvars;
    end

endmodule

SelfcheckingTB/cla_directed_tb.vcd
$date
   Fri Dec  6 19:41:40 2024
$end

$version
  2024.1
  $dumpfile ("cla_directed_tb.vcd") 
$end

$timescale
  1ps
$end

$scope module cla_top_tb $end
$var reg 16 ! a [15:0] $end
$var reg 16 " b [15:0] $end
$var reg 1 # cin $end
$var reg 1 $ clk $end
$var reg 16 % sum [15:0] $end
$var reg 1 & carry_out16 $end
$scope module dut $end
$var wire 16 ' a [15:0] $end
$var wire 16 ( b [15:0] $end
$var wire 1 ) cin $end
$var wire 1 * clk $end
$var reg 16 % sum [15:0] $end
$var wire 1 + carry_out16 $end
$var wire 16 , g [15:0] $end
$var wire 16 - p [15:0] $end
$var wire 4 . cout1 [3:0] $end
$var wire 4 / cout2 [3:0] $end
$var wire 4 0 cout3 [3:0] $end
$var wire 4 1 cout4 [3:0] $end
$var wire 1 2 cout_mid1 $end
$var wire 1 3 cout_mid2 $end
$var wire 1 4 cout_mid3 $end
$scope module gen_prop_inst $end
$var wire 16 ' a [15:0] $end
$var wire 16 ( b [15:0] $end
$var wire 16 , g [15:0] $end
$var wire 16 - p [15:0] $end
$upscope $end
$scope module carry_unit1 $end
$var wire 4 5 g [3:0] $end
$var wire 4 6 p [3:0] $end
$var wire 1 ) cin $end
$var wire 4 . cout [3:0] $end
$upscope $end
$scope module carry_unit2 $end
$var wire 4 7 g [7:4] $end
$var wire 4 8 p [7:4] $end
$var wire 1 2 cin $end
$var wire 4 / cout [3:0] $end
$upscope $end
$scope module carry_unit3 $end
$var wire 4 9 g [11:8] $end
$var wire 4 : p [11:8] $end
$var wire 1 3 cin $end
$var wire 4 0 cout [3:0] $end
$upscope $end
$scope module carry_unit4 $end
$var wire 4 ; g [15:12] $end
$var wire 4 < p [15:12] $end
$var wire 1 4 cin $end
$var wire 4 1 cout [3:0] $end
$upscope $end
$scope module sum_unit $end
$var wire 16 - p [15:0] $end
$var wire 1 ) cin $end
$var wire 16 = cout [15:0] $end
$var wire 1 * clk $end
$var reg 16 % sum [15:0] $end
$var wire 1 + carry_out16 $end
$var integer 32 > i [31:0] $end
$upscope $end
$upscope $end
$scope task check_output $end
$var reg 17 ? expected_sum [16:0] $end
$upscope $end
$upscope $end
$enddefinitions $end

#0
$dumpvars
bx !
bx "
x#
0$
bx %
x&
bx '
bx (
x)
0*
x+
bx ,
bx -
bx .
bx /
bx 0
bx 1
x2
x3
x4
bx 5
bx 6
bx 7
bx 8
bx 9
bx :
bx ;
bx <
bx =
bx >
bx ?
$end

#5000
1$
1*
b10000 >

#10000
b1010 !
b1100 "
0#
0$
0&
b1010 '
b1100 (
0)
0*
0+
b1000 ,
b110 -
b1000 .
b0 /
b0 0
b0 1
12
03
04
b1000 5
b110 6
b0 7
b0 8
b0 9
b0 :
b0 ;
b0 <
b1000 =

#15000
1$
b10110 %
1*
b10000 >

#20000
b111110100 !
b1001011000 "
0$
b111110100 '
b1001011000 (
0*
b1010000 ,
b1110101100 -
b0 .
b1111 /
b11 0
02
13
b0 5
b1100 6
b101 7
b1010 8
b0 9
b11 :
b0 ;
b0 <
b1111110000 =
b10110 ?

#25000
1$
b10001001100 %
1*
b10000 >

#30000
b111011100100100 !
b101000000010011 "
1#
0$
b111011100100100 '
b101000000010011 (
1)
0*
b101000000000000 ,
b10011100110111 -
b111 .
b0 /
b0 0
b111 1
03
b0 5
b111 6
b0 7
b11 8
b0 9
b111 :
b101 ;
b10 <
b111000000000111 =
b10001001100 ?

#35000
1$
b1100011100111000 %
1*
b10000 >

#40000
b1111110111101000 !
b1010 "
0$
0&
b1111110111101000 '
b1010 (
0*
0+
b1000 ,
b1111110111100010 -
b1000 .
b0 1
12
b1000 5
b10 6
b0 7
b1110 8
b0 9
b1101 :
b0 ;
b1111 <
b1000 =
b1100011100111000 ?

#45000
1$
b1111110111110011 %
1*
b10000 >

#50000
b0 !
b0 "
0$
b0 '
b0 (
0*
b0 ,
b0 -
b0 .
02
b0 5
b0 6
b0 7
b0 8
b0 9
b0 :
b0 ;
b0 <
b0 =
b1111110111110011 ?

#55000
1$
b1 %
1*
b10000 >

#60000
b1111111001100000 !
b101110111000 "
0$
1&
b1111111001100000 '
b101110111000 (
0*
1+
b101000100000 ,
b1111010111011000 -
b1110 /
b1111 0
b1111 1
13
14
b0 5
b1000 6
b10 7
b1101 8
b1010 9
b101 :
b0 ;
b1111 <
b1111111111100000 =
b1 ?

#65000
1$
b101000011001 %
1*
b10000 >

#70000
b1111111111111111 !
b0 "
0$
1&
b1111111111111111 '
b0 (
0*
1+
b0 ,
b1111111111111111 -
b1111 .
b1111 /
b1111 0
b1111 1
12
13
14
b0 5
b1111 6
b0 7
b1111 8
b0 9
b1111 :
b0 ;
b1111 <
b1111111111111111 =
b10000101000011001 ?

#75000
1$
b0 %
1*
b10000 >

#80000
0$
0*
b10000000000000000 ?

#85000
1$
1*
b10000 >
